{
    "Laptops": {
        "brand": "String. Extract the brand name (e.g., HP, Dell, Lenovo).",
        "series": "String. Extract the model family/series (e.g., Victus, Latitude, ThinkPad).",
        "model": "String. Extract the specific model number.",
        "processor_brand": "String. Extract full CPU brand(e.g Intel, AMD",
        "processor_name": "String. Extract the full CPU name (e.g., Core i7-13700H, Ryzen 7 5800H).",
        "processor_speed_ghz": "Float. Extract the base or max clock speed in GHz.",
        "processor_cache_mb": "Integer. Extract the CPU cache size in MB.",
        "ram_gb": "Integer. Total installed RAM in GB.",
        "ram_type": "String. Extract the RAM generation (e.g., DDR4, DDR5).",
        "max_ram_gb": "Integer. Extract the maximum supported RAM in GB if listed.",
        "storage_ssd_gb": "Integer. Total SSD storage in GB (convert 1TB to 1024).",
        "storage_hdd_gb": "Integer. Total HDD storage in GB (convert 1TB to 1024).",
        "has_optical_drive": "Boolean. True if a CD/DVD/Optical drive is explicitly mentioned.",
        "graphics_card_brand":"String. Extract full GPU brand(e.g NNvidia, Intel, AMD",
        "graphics_card_name": "String. Extract the full GPU name (e.g., RTX 4060, Iris Xe).",
        "graphics_memory_gb": "Integer. Dedicated GPU memory in GB (Return null for integrated graphics).",
        "screen_size_inches": "Float. Screen diagonal in inches (e.g., 15.6).",
        "screen_resolution": "String. Extract the resolution (e.g., 1920x1080, 4K, FHD).",
        "has_wifi": "Boolean. True if Wi-Fi is mentioned.",
        "has_bluetooth": "Boolean. True if Bluetooth is mentioned.",
        "has_lan": "Boolean. True if LAN, RJ45, or Ethernet is mentioned.",
        "has_hdmi": "Boolean. True if HDMI is mentioned.",
        "has_vga": "Boolean. True if VGA is mentioned.",
        "has_usb_type_c": "Boolean. True if USB-C or Thunderbolt is mentioned.",
        "has_usb_type_a": "Boolean. True if standard USB (2.0, 3.0, 3.1, 3.2) is mentioned.",
        "supports_docking": "Boolean. True if docking station support is explicitly mentioned.",
        "has_webcam": "Boolean. True if a webcam or camera is mentioned.",
        "has_backlit_keyboard": "Boolean. True if the keyboard is backlit.",
        "is_spill_resistant": "Boolean. True if the keyboard is spill-resistant.",
        "has_fingerprint_reader": "Boolean. True if a fingerprint reader or biometric security is mentioned.",
        "audio_features": "String. Extract any specific branded audio details.",
        "weight_kg": "Float. Extract weight in kilograms.",
        "dimensions": "String. Extract the physical dimensions.",
        "battery_wh": "Float. Extract the battery capacity in Watt-hours (Wh) or cells.",
        "power_supply_w": "Float. Extract the AC adapter/power supply wattage in Watts.",
        "os_version": "String. Extract the operating system.",
        "warranty": "String. Extract warranty duration/details."
    },
    "Chargers": {
        "brand": "String. Extract the brand name.",
        "model": "String. Extract the specific model number.",
        "max_output_w": "Float. Extract absolute MAXIMUM total output wattage. Calculate V * A = W if needed.",
        "max_input_v": "Float. Extract the maximum supported input voltage (e.g., 240 for 100-240V).",
        "has_pd": "Boolean. True if Power Delivery (PD) is explicitly mentioned.",
        "has_pps": "Boolean. True if Programmable Power Supply (PPS) is mentioned.",
        "has_qc": "Boolean. True if Quick Charge (QC) is mentioned.",
        "total_ports": "Integer. Total number of charging output ports.",
        "ports_type_c": "Integer. Extract the exact number of USB-C / Type-C ports.",
        "ports_usb_a": "Integer. Extract the exact number of USB-A ports.",
        "is_gan": "Boolean. True if GaN (Gallium Nitride) technology is mentioned.",
        "has_wireless_charging": "Boolean. True if it supports wireless or MagSafe charging.",
        "includes_cable": "Boolean. True if the charger comes with a cable.",
        "plug_type": "String. Extract the wall plug standard if mentioned.",
        "weight_g": "Integer. Extract weight in grams.",
        "warranty": "String. Extract warranty details."
    },
    "Smartwatches": {
        "brand": "String. Extract the brand name.",
        "screen_size_inches": "Float. Screen size in inches.",
        "battery_capacity_mah": "Integer. Battery capacity in mAh.",
        "has_calling": "Boolean. True if it supports Bluetooth calling.",
        "is_waterproof": "Boolean. True if it explicitly mentions IP rating or waterproof."
    },
    "Data Cables": {
        "brand": "String. Extract the brand name.",
        "model": "String. Extract the specific model number.",
        "connector_in": "String. Extract the input connector type (e.g., USB-A, USB-C).",
        "connector_out": "String. Extract the output connector type (e.g., USB-C, Lightning, Micro-USB).",
        "max_current_a": "Float. Extract the maximum supported current in Amps (e.g., 3A, 5A).",
        "max_power_w": "Float. Extract maximum supported wattage. Calculate V * A = W if needed.",
        "data_transfer_mbps": "Integer. Extract data transfer speed in Mbps (Convert Gbps to Mbps).",
        "length_m": "Float. Extract cable length in meters. Convert cm/feet to meters.",
        "material": "String. Extract the primary build material.",
        "has_digital_display": "Boolean. True if the cable features a built-in display.",
        "is_magnetic": "Boolean. True if it is a magnetic detachable charging cable."
    },
    "Multifunction Adapters": {
        "brand": "String. Extract the brand name.",
        "model": "String. Extract the specific model number.",
        "host_interface": "String. Extract the connector that plugs into the computer/phone.",
        "total_ports": "Integer. Total number of expansion ports on the adapter.",
        "ports_usb_a": "Integer. Exact number of USB-A ports.",
        "ports_type_c": "Integer. Exact number of USB-C data ports.",
        "has_hdmi": "Boolean. True if an HDMI port is included.",
        "max_hdmi_resolution": "String. Extract the maximum supported display resolution and refresh rate.",
        "has_vga": "Boolean. True if a VGA port is included.",
        "supports_pd_passthrough": "Boolean. True if it supports PD passthrough charging.",
        "max_pd_w": "Float. Extract the maximum PD passthrough wattage.",
        "has_ethernet": "Boolean. True if an RJ45/Ethernet/LAN port is included.",
        "has_sd_reader": "Boolean. True if an SD or TF/MicroSD card reader is included.",
        "has_audio_jack": "Boolean. True if a 3.5mm audio jack is included.",
        "cable_length_m": "Float. Extract the length of the built-in host cable in meters, if applicable."
    },
    "Convertors": {
        "brand": "String. Extract the brand name.",
        "model": "String. Extract the specific model number.",
        "connector_in": "String. Extract the input/source connector.",
        "connector_out": "String. Extract the output/target connector.",
        "is_bidirectional": "Boolean. True if the converter works in both directions.",
        "max_video_resolution": "String. Extract the maximum supported display resolution if it's a video converter.",
        "data_transfer_mbps": "Integer. Extract data transfer speed in Mbps if it's a data converter.",
        "has_audio_passthrough": "Boolean. True if the converter explicitly mentions carrying audio.",
        "supports_pd_passthrough": "Boolean. True if it supports Power Delivery (PD) charging.",
        "cable_length_m": "Float. Extract the length of the cable in meters."
    },
    "Mix Gadgets": {
        "brand": "String. Extract the brand name.",
        "model": "String. Extract the specific model number.",
        "gadget_type": "String. Classify into ONE of: [Monitor Mount, Barcode Scanner, Presenter/Laser Pointer, E-Scooter/Rideable, Smart Home Device, Other Electronics, Non-Electronic Accessory].",
        "is_rechargeable": "Boolean. True if the item has a rechargeable battery.",
        "battery_capacity_mah": "Integer. Battery capacity in mAh.",
        "power_consumption_w": "Float. Extract max power consumption, wattage, or motor power in Watts.",
        "connection_type": "String. MUST be one of: [Wired USB, Bluetooth, Wireless 2.4GHz, Wi-Fi, None].",
        "weight_kg": "Float. Extract weight in kilograms.",
        "max_load_kg": "Float. Extract the maximum weight capacity/load in kilograms.",
        "ip_rating": "String. Extract the waterproof/dustproof IP rating if available.",
        "has_display_screen": "Boolean. True if the gadget has an LCD, OLED, or LED display screen."
    },
    "Stereo Handsfree": {
        "brand": "String. Extract the brand name.",
        "model": "String. Extract the specific model number.",
        "connector_type": "String. MUST be one of: [3.5mm Jack, USB-C, Lightning, 2.5mm Jack].",
        "cable_length_m": "Float. Extract the cable/cord length in meters.",
        "wearing_style": "String. MUST be one of: [In-Ear, Half-Ear, Earbud].",
        "driver_size_mm": "Float. Extract the speaker/driver unit diameter in millimeters.",
        "impedance_ohms": "Integer. Extract the AC Impedance or Resistance in Ohms (\u03a9).",
        "sensitivity_db": "Integer. Extract the audio sensitivity in Decibels (dB).",
        "has_microphone": "Boolean. True if it has a built-in mic.",
        "has_inline_controls": "Boolean. True if it has volume controls or a multi-function button on the wire.",
        "has_anc": "Boolean. True if it explicitly features Active Noise Cancellation (ANC)."
    },
    "Ring Lights": {
        "brand": "String. Extract the brand name.",
        "model": "String. Extract the specific model number.",
        "ring_diameter_inches": "Float. Extract the outer diameter of the ring light in inches.",
        "includes_tripod": "Boolean. True if it comes with a tripod stand.",
        "includes_phone_holder": "Boolean. True if it comes with a mount/holder for a smartphone.",
        "has_adjustable_color_temp": "Boolean. True if it mentions adjustable color temperatures.",
        "has_rgb": "Boolean. True if it mentions RGB or multi-color modes.",
        "power_source": "String. MUST be one of: [USB, AC Power/Wall Plug, Battery].",
        "has_remote_control": "Boolean. True if an inline remote or wireless remote control is included."
    },
    "Gaming Accessories": {
        "brand": "String. Extract the brand name.",
        "model": "String. Extract the specific model number.",
        "gaming_device_type": "String. Classify into ONE of: [Mouse, Keyboard, Headset, Controller, Cooling Pad/Fan, Other].",
        "connection_type": "String. MUST be one of: [Wired, Wireless 2.4GHz, Bluetooth, Dual-Mode].",
        "has_rgb": "Boolean. True if it features RGB, LED, or backlit lighting.",
        "max_dpi": "Integer. Extract the maximum DPI/CPI resolution for mice.",
        "polling_rate_hz": "Integer. Extract the polling rate or report rate in Hz.",
        "number_of_buttons": "Integer. Total number of programmable buttons or keys.",
        "switch_type": "String. Extract the mechanical switch type or keycap technology.",
        "switch_lifespan_millions": "Float. Extract the key/micro-switch lifespan in millions of clicks.",
        "driver_size_mm": "Float. Extract the speaker/driver unit diameter in millimeters.",
        "has_microphone": "Boolean. True if it includes a built-in microphone."
    },
    "Laptop Stands & Cooling Pads": {
        "brand": "String. Extract the brand name.",
        "model": "String. Extract the specific model number.",
        "max_laptop_size_inches": "Float. Extract the maximum supported laptop size in inches.",
        "number_of_fans": "Integer. Extract the total number of cooling fans. Output 0 if it is just a stand.",
        "is_adjustable": "Boolean. True if the height or viewing angle is adjustable.",
        "has_rgb": "Boolean. True if it mentions RGB or LED lighting.",
        "material": "String. Extract the primary build material.",
        "weight_g": "Integer. Extract the weight of the stand/pad in grams."
    },
    "Bluetooth Handsfree": {
        "brand": "String. Extract the brand name.",
        "model": "String. Extract the specific model number.",
        "bluetooth_version": "Float. Extract the Bluetooth version.",
        "playtime_hours": "Float. Extract the maximum music/play time in hours on a single charge.",
        "battery_capacity_buds_mah": "Integer. Extract the battery capacity of a single earbud in mAh.",
        "battery_capacity_case_mah": "Integer. Extract the battery capacity of the charging case in mAh.",
        "driver_size_mm": "Float. Extract the speaker/driver size in millimeters.",
        "has_anc": "Boolean. True if Active Noise Cancellation (ANC) is explicitly featured.",
        "has_enc": "Boolean. True if Environmental Noise Cancellation (ENC) or clear call tech is mentioned.",
        "ip_rating": "String. Extract the waterproof/dustproof IP rating."
    },
    "General": {
        "brand": "String. Extract the brand name.",
        "weight_kg": "Float. Extract weight in kilograms if available.",
        "power_w": "Float. Extract general wattage if applicable."
    },
    "Keyboards and Mouse": {
        "brand": "String. Extract the brand name.",
        "model": "String. Extract the specific model number.",
        "device_type": "String. Classify into ONE of: [Keyboard, Mouse, Combo].",
        "connection_type": "String. MUST be one of: [Wired, Wireless 2.4GHz, Bluetooth, Dual-Mode].",
        "has_rgb": "Boolean. True if it explicitly features RGB, LED, or backlit lighting.",
        "is_mechanical": "Boolean. True if the keyboard uses mechanical switches.",
        "switch_type": "String. Extract the switch color/type (e.g., Blue, Red, Brown, Membrane).",
        "number_of_keys": "Integer. Total number of keys on the keyboard (e.g., 104, 87, 61).",
        "max_dpi": "Integer. Extract the maximum DPI/CPI resolution for mice.",
        "number_of_buttons": "Integer. Total number of buttons on the mouse.",
        "polling_rate_hz": "Integer. Extract the polling rate in Hz (e.g., 1000).",
        "cable_length_m": "Float. Extract the cable length in meters.",
        "battery_life_days": "Float. Extract battery life in days for wireless devices (convert hours/months to days).",
        "weight_g": "Integer. Extract weight in grams."
    },
    "Speakers and Headphones": {
        "brand": "String. Extract the brand name.",
        "model": "String. Extract the specific model number.",
        "device_type": "String. Classify into ONE of: [Portable Speaker, Desktop/Multimedia Speaker, Soundbar, Over-Ear Headphones, On-Ear Headphones].",
        "connection_type": "String. MUST be one of: [Wired, Bluetooth, Wi-Fi, Multi-Mode].",
        "audio_output_power_w": "Float. Extract the RMS or maximum audio output power in Watts (Crucial for speakers).",
        "driver_size_mm": "Float. Extract the speaker/driver unit diameter in millimeters.",
        "impedance_ohms": "Integer. Extract the AC Impedance or Resistance in Ohms (\u03a9).",
        "frequency_response_min_hz": "Integer. Extract the LOWEST number in the frequency response range (e.g., 20 from 20Hz-20kHz).",
        "frequency_response_max_hz": "Integer. Extract the HIGHEST number in the frequency response range (e.g., 20000 from 20Hz-20kHz. Convert kHz to Hz).",
        "playtime_hours": "Float. Extract the maximum music/play time in hours on a single charge.",
        "battery_capacity_mah": "Integer. Battery capacity in mAh.",
        "has_microphone": "Boolean. True if it has a built-in microphone for calls.",
        "has_anc": "Boolean. True if Active Noise Cancellation (ANC) is explicitly featured.",
        "ip_rating": "String. Extract the waterproof/dustproof IP rating (e.g., IPX7, IP67)."
    },
    "Extension Leads & Smart Switches": {
        "brand": "String. Extract the brand name.",
        "model": "String. Extract the specific model number.",
        "total_ac_outlets": "Integer. Total number of standard AC power sockets.",
        "total_usb_ports": "Integer. Total number of USB charging ports (Combine USB-A and USB-C).",
        "max_power_w": "Float. Extract the maximum rated power in Watts (e.g., 2500W, 3200W).",
        "max_current_a": "Float. Extract the maximum rated current in Amps (e.g., 10A, 16A).",
        "cable_length_m": "Float. Extract the power cord length in meters.",
        "is_smart_device": "Boolean. True if Wi-Fi, App control, or Voice control (Alexa/Google) is explicitly mentioned.",
        "has_surge_protection": "Boolean. True if surge, overload, or lightning protection is mentioned."
    },
    "Mobile Holders": {
        "brand": "String. Extract the brand name.",
        "model": "String. Extract the specific model number.",
        "holder_type": "String. Classify into ONE of: [Car Mount, Desk Stand, Bike/Motorcycle Mount, Tripod/Selfie Stick, Ring/Pop Socket].",
        "mounting_mechanism": "String. Classify into ONE of: [Magnetic/MagSafe, Clamp/Grip, Suction Cup, Adhesive, Air Vent Clip].",
        "has_wireless_charging": "Boolean. True if it doubles as a wireless charger.",
        "is_adjustable": "Boolean. True if it explicitly mentions 360-degree rotation, tilt, or telescopic arms.",
        "material": "String. Extract the primary build material."
    },
    "Multifunction Hubs & Docks": {
        "brand": "String. Extract the brand name.",
        "model": "String. Extract the specific model number.",
        "host_interface": "String. Extract the connector that plugs into the computer/phone (e.g., USB-C, USB-A).",
        "total_ports": "Integer. Total number of expansion ports on the adapter.",
        "ports_usb_a": "Integer. Exact number of USB-A ports.",
        "ports_type_c": "Integer. Exact number of USB-C data ports.",
        "has_hdmi": "Boolean. True if an HDMI port is included.",
        "max_hdmi_resolution": "String. Extract the maximum supported display resolution and refresh rate (e.g., 4K@60Hz, 1080p).",
        "has_vga": "Boolean. True if a VGA port is included.",
        "supports_pd_passthrough": "Boolean. True if the adapter supports Power Delivery (PD) passthrough charging.",
        "max_pd_w": "Float. Extract the maximum PD passthrough wattage.",
        "has_ethernet": "Boolean. True if an RJ45/Ethernet/LAN port is included.",
        "has_sd_reader": "Boolean. True if an SD or TF/MicroSD card reader is included.",
        "has_audio_jack": "Boolean. True if a 3.5mm audio jack is included.",
        "cable_length_m": "Float. Extract the length of the built-in host cable in meters, if applicable."
    },
    "USB Cards & Devices": {
        "brand": "String. Extract the brand name.",
        "model": "String. Extract the specific model number.",
        "device_type": "String. Classify into ONE of: [Wi-Fi Adapter, Bluetooth Adapter, Sound Card, Video Capture Card, USB Expansion Card, Other].",
        "host_interface": "String. Extract the connector that plugs into the computer (e.g., USB-A, USB-C, PCIe).",
        "wireless_standard": "String. Extract Wi-Fi or Bluetooth generation if applicable (e.g., Wi-Fi 6, Bluetooth 5.0).",
        "max_speed_mbps": "Integer. Extract maximum data or network speed in Mbps.",
        "has_antenna": "Boolean. True if it features an external antenna."
    },
    "Card Readers": {
        "brand": "String. Extract the brand name.",
        "model": "String. Extract the specific model number.",
        "host_interface": "String. Extract the connector that plugs into the computer/phone (e.g., USB-A, USB-C, Lightning).",
        "supported_card_formats": "String. Extract the types of memory cards supported (e.g., SD, MicroSD, TF, CF).",
        "number_of_slots": "Integer. Total number of card slots available.",
        "max_read_speed_mbps": "Integer. Extract maximum read speed in MB/s or Mbps (Convert MB/s to Mbps by multiplying by 8 if you want strict Mbps, or just state the number).",
        "is_otg_supported": "Boolean. True if it supports OTG (On-The-Go) for mobile phones."
    },
    "Android BOX & Screen Mirror": {
        "brand": "String. Extract the brand name.",
        "model": "String. Extract the specific model number.",
        "device_type": "String. Classify into ONE of: [Android TV Box, Screen Mirroring Dongle/AnyCast].",
        "max_video_resolution": "String. Extract the maximum supported display resolution and refresh rate (e.g., 4K@60Hz, 8K, 1080p).",
        "os_version": "String. Extract the operating system version (e.g., Android 11, Android TV 10).",
        "processor_chipset": "String. Extract the CPU/Chipset model if listed (e.g., Amlogic S905X4, Rockchip).",
        "ram_gb": "Integer. Total installed RAM in GB.",
        "storage_gb": "Integer. Total internal storage (ROM/Flash) in GB.",
        "has_wifi": "Boolean. True if Wi-Fi is mentioned (usually Dual Band 2.4/5G).",
        "has_bluetooth": "Boolean. True if Bluetooth is mentioned.",
        "has_ethernet": "Boolean. True if an RJ45/LAN port is included.",
        "includes_remote": "Boolean. True if it comes with a remote control."
    },
    "Recording Accessories": {
        "brand": "String. Extract the brand name.",
        "model": "String. Extract the specific model number.",
        "device_type": "String. Classify into ONE of: [Wireless Presenter/Laser Pointer, Microphone/Audio Recorder, Other].",
        "connection_type": "String. MUST be one of: [Wired, Wireless USB Receiver, Bluetooth].",
        "connector_in": "String. Extract the connector type if it plugs into a device (e.g., USB-A, USB-C, 3.5mm, Lightning).",
        "control_distance_m": "Float. Extract the maximum wireless control or laser distance in meters.",
        "laser_color": "String. Extract the laser pointer color if applicable (e.g., Red, Green).",
        "power_source": "String. Extract the battery type (e.g., Rechargeable, AAA Battery)."
    },
    "USB Hubs": {
        "brand": "String. Extract the brand name.",
        "model": "String. Extract the specific model number.",
        "host_interface": "String. Extract the connector that plugs into the computer (e.g., USB-A, USB-C).",
        "total_usb_ports": "Integer. Total number of USB expansion ports.",
        "ports_usb_a": "Integer. Exact number of USB-A ports.",
        "ports_type_c": "Integer. Exact number of USB-C data ports.",
        "max_data_speed_mbps": "Integer. Extract maximum data transfer speed in Mbps (e.g., 5Gbps = 5000).",
        "has_external_power_input": "Boolean. True if the hub has a dedicated power input port (DC or PD) to power multiple heavy devices.",
        "cable_length_m": "Float. Extract the length of the built-in cable in meters."
    },
    "Power Banks": {
        "brand": "String. Extract the brand name.",
        "model": "String. Extract the specific model number.",
        "capacity_mah": "Integer. Highest advertised capacity in mAh.",
        "max_input_w": "Float. Extract ONLY the max input wattage. Do NOT confuse with output.",
        "max_output_w": "Float. Extract ONLY the max output wattage. IF given in Volts and Amps, calculate V * A = W. Do NOT confuse with input.",
        "total_ports": "Integer. Total number of charging output ports (USB-A + USB-C).",
        "has_wireless_charging": "Boolean. True if it supports magnetic or wireless charging.",
        "has_built_in_cable": "Boolean. True if it has built-in charging cables.",
        "is_solar_powered": "Boolean. True if it features solar charging panels."
    },
    "Tripods & Selfie Sticks": {
        "brand": "String. Extract the brand name.",
        "model": "String. Extract the specific model number.",
        "device_type": "String. Classify into ONE of: [Tripod, Selfie Stick, Gimbal/Stabilizer, Vlogging Kit].",
        "max_extended_length_cm": "Integer. Extract the maximum extended length in centimeters. (Convert inches or meters to cm).",
        "folded_length_cm": "Integer. Extract the folded/collapsed length in centimeters.",
        "max_load_kg": "Float. Extract the maximum weight capacity/load in kilograms.",
        "material": "String. Extract the primary build material (e.g., Aluminum, Carbon Fiber, ABS).",
        "has_bluetooth_remote": "Boolean. True if it includes a wireless Bluetooth shutter remote.",
        "has_fill_light": "Boolean. True if it has a built-in ring light or fill light.",
        "is_gimbal_stabilizer": "Boolean. True if it features active motor stabilization (Gimbal)."
    },
    "Network Adapters & Accessories": {
        "brand": "String. Extract the brand name.",
        "model": "String. Extract the specific model number.",
        "device_type": "String. Classify into ONE of: [Wi-Fi Adapter, Ethernet/LAN Adapter, Bluetooth Adapter].",
        "host_interface": "String. Extract the connector that plugs into the computer (e.g., USB-A, USB-C, PCIe).",
        "wireless_standard": "String. Extract Wi-Fi or Bluetooth generation if applicable (e.g., Wi-Fi 6, 802.11ac, Bluetooth 5.3).",
        "max_network_speed_mbps": "Integer. Extract maximum network speed in Mbps (Convert Gbps to Mbps, e.g., 1Gbps = 1000).",
        "number_of_antennas": "Integer. Total number of external antennas.",
        "antenna_gain_dbi": "Float. Extract the antenna gain in dBi if mentioned.",
        "has_bluetooth": "Boolean. True if a Wi-Fi adapter also includes Bluetooth functionality."
    },
    "Smart Projectors": {
        "brand": "String. Extract the brand name.",
        "model": "String. Extract the specific model number.",
        "native_resolution": "String. Extract the TRUE optical native resolution (e.g., 1080p, 720p, 4K). Do not confuse with 'supported' resolution.",
        "max_supported_resolution": "String. Extract the maximum supported decoding resolution.",
        "brightness_lumens": "Integer. Extract the brightness in Lumens or ANSI Lumens.",
        "contrast_ratio": "String. Extract the contrast ratio (e.g., 10000:1).",
        "lamp_life_hours": "Integer. Extract the expected lamp/bulb life in hours.",
        "max_projection_size_inches": "Integer. Extract the maximum projection screen size in inches.",
        "os_version": "String. Extract the smart operating system (e.g., Android 9.0, Android TV).",
        "ram_gb": "Integer. Total installed RAM in GB.",
        "storage_gb": "Integer. Total internal storage (ROM) in GB.",
        "has_wifi": "Boolean. True if Wi-Fi or wireless screen mirroring is supported.",
        "has_auto_keystone": "Boolean. True if it explicitly mentions Auto Keystone correction.",
        "has_built_in_speaker": "Boolean. True if it has built-in audio/speakers."
    },
    "External Enclosures": {
        "brand": "String. Extract the brand name.",
        "model": "String. Extract the specific model number.",
        "supported_drive_size": "String. Classify into ONE of: [2.5-inch, 3.5-inch, M.2, Mixed].",
        "supported_drive_interface": "String. Classify into ONE of: [SATA, NVMe, SATA/NVMe Dual].",
        "host_interface": "String. Extract the connector that plugs into the computer (e.g., USB-C, USB-A).",
        "max_speed_gbps": "Integer. Extract maximum data transfer speed in Gbps (e.g., 5, 10, 20, 40).",
        "max_capacity_tb": "Integer. Extract the maximum supported drive capacity in Terabytes (TB).",
        "material": "String. Extract the primary build material (e.g., Aluminum, Transparent PC, ABS).",
        "is_tool_free": "Boolean. True if it explicitly mentions tool-free or plug-and-play installation."
    },
    "Laptop Bags": {
        "brand": "String. Extract the brand name.",
        "model": "String. Extract the specific model number.",
        "bag_type": "String. Classify into ONE of: [Backpack, Sleeve, Briefcase/Messenger, Hard Case].",
        "max_laptop_size_inches": "Float. Extract the maximum supported laptop size in inches (e.g., 15.6, 17.3, 14.0).",
        "material": "String. Extract the primary build material (e.g., Polyester, Nylon, Leather, Neoprene).",
        "is_water_resistant": "Boolean. True if it explicitly mentions being waterproof, water-resistant, or splash-proof."
    },
    "SSDs": {
        "brand": "String. Extract the brand name.",
        "model": "String. Extract the specific model number.",
        "storage_gb": "Integer. Total storage capacity in GB (Convert TB to GB, e.g., 1TB = 1024, 2TB = 2048).",
        "form_factor": "String. Classify into ONE of: [2.5-inch, M.2 2280, M.2 2230, Portable/External, mSATA].",
        "interface": "String. Classify into ONE of: [SATA III, PCIe 3.0 NVMe, PCIe 4.0 NVMe, PCIe 5.0 NVMe, USB-C].",
        "max_read_speed_mbps": "Integer. Extract maximum read speed in MB/s.",
        "max_write_speed_mbps": "Integer. Extract maximum write speed in MB/s.",
        "is_external": "Boolean. True if it is a portable/external SSD rather than an internal drive."
    },
    "Softwares": {
        "brand": "String. Extract the software developer/brand (e.g., Microsoft, Adobe, Kaspersky).",
        "software_type": "String. Classify into ONE of: [Operating System, Antivirus/Security, Office/Productivity, Design/Creative, Utility, Other].",
        "license_duration_months": "Integer. Extract the duration of the license in months. Use 999 for Lifetime/Perpetual licenses (e.g., 1 Year = 12).",
        "number_of_devices": "Integer. Extract the number of PCs/Devices the license covers.",
        "delivery_method": "String. Classify into ONE of: [Digital Download/Key, Physical USB/CD Box].",
        "os_compatibility": "String. Extract the supported OS (e.g., Windows 11, macOS, Android)."
    },
    "Graphic Tablets": {
        "brand": "String. Extract the brand name (e.g., Wacom, Huion, XP-Pen).",
        "model": "String. Extract the specific model number.",
        "has_display_screen": "Boolean. True if it is a pen display (has a built-in monitor). False if it is a standard drawing pad.",
        "active_area_diagonal_inches": "Float. Extract the active drawing area diagonal in inches. (Convert cm to inches if necessary).",
        "pressure_levels": "Integer. Extract the pen pressure sensitivity levels (e.g., 4096, 8192).",
        "resolution_lpi": "Integer. Extract the reading resolution in LPI (Lines Per Inch).",
        "report_rate_pps": "Integer. Extract the report rate in PPS or RPS (Points/Reports Per Second).",
        "has_tilt_support": "Boolean. True if the pen supports tilt recognition.",
        "is_wireless": "Boolean. True if the tablet supports wireless/Bluetooth connectivity.",
        "number_of_shortcut_keys": "Integer. Total number of customizable express/shortcut keys/buttons.",
        "includes_pen": "Boolean. True if a stylus/pen is included in the box."
    },
    "Smart Watches & Bands": {
        "brand": "String. Extract the brand name.",
        "model": "String. Extract the specific model number.",
        "device_type": "String. Classify into ONE of: [Smartwatch, Fitness Band/Tracker].",
        "screen_size_inches": "Float. Screen size in inches.",
        "panel_type": "String. Extract the display panel tech if mentioned (e.g., AMOLED, OLED, LCD, IPS).",
        "battery_capacity_mah": "Integer. Battery capacity in mAh.",
        "battery_life_days": "Float. Extract the maximum advertised battery life in days (convert hours to days).",
        "has_calling": "Boolean. True if it supports Bluetooth calling or has a built-in mic/speaker.",
        "has_gps": "Boolean. True if it features built-in standalone GPS.",
        "has_heart_rate_monitor": "Boolean. True if it tracks heart rate.",
        "has_spo2_monitor": "Boolean. True if it explicitly tracks Blood Oxygen / SpO2.",
        "is_waterproof": "Boolean. True if it explicitly mentions an IP rating or ATM water resistance (e.g., IP68, 5ATM)."
    },
    "Gaming Sticks": {
        "brand": "String. Extract the brand name.",
        "model": "String. Extract the specific model number.",
        "number_of_built_in_games": "Integer. Total number of pre-installed games (e.g., 10000).",
        "max_video_resolution": "String. Extract the maximum supported display resolution (e.g., 4K, 1080p).",
        "storage_gb": "Integer. Total internal storage or included TF/MicroSD card capacity in GB.",
        "ram_gb": "Integer. Total installed RAM in GB.",
        "number_of_controllers": "Integer. Number of included gamepads/controllers.",
        "is_wireless_controller": "Boolean. True if the included controllers are wireless.",
        "supported_emulators": "String. Extract the list of supported console emulators if mentioned (e.g., PS1, GBA, MAME)."
    },
    "Smart Cameras": {
        "brand": "String. Extract the brand name.",
        "model": "String. Extract the specific model number.",
        "camera_type": "String. Classify into ONE of: [Indoor Security, Outdoor Security, Action Camera, Dash Cam, Webcam].",
        "max_video_resolution": "String. Extract the maximum video capture resolution (e.g., 1080p, 2K, 4K).",
        "field_of_view_degrees": "Integer. Extract the lens viewing angle or field of view in degrees.",
        "has_night_vision": "Boolean. True if infrared (IR) or color night vision is mentioned.",
        "has_motion_detection": "Boolean. True if it explicitly mentions motion detection or tracking.",
        "has_two_way_audio": "Boolean. True if it has both a mic and speaker for two-way talk.",
        "supports_sd_card": "Boolean. True if it supports local TF/MicroSD card storage.",
        "is_ptz": "Boolean. True if it supports Pan-Tilt-Zoom (PTZ) motor rotation.",
        "ip_rating": "String. Extract the waterproof/dustproof IP rating if available (e.g., IP65, IP66)."
    },
    "Batteries": {
        "brand": "String. Extract the brand name.",
        "model": "String. Extract the specific model number or replacement part number.",
        "battery_form_factor": "String. Classify into ONE of: [Replacement/Custom, AA, AAA, 18650, Coin Cell, Power Tool, Other Standard].",
        "battery_chemistry": "String. Extract the chemistry (e.g., Lithium-Ion, NiMH, Alkaline, Li-Polymer).",
        "capacity_mah": "Integer. Extract battery capacity in mAh.",
        "voltage_v": "Float. Extract the battery voltage in Volts.",
        "energy_wh": "Float. Extract the energy capacity in Watt-hours (Wh) if provided.",
        "number_of_cells": "Integer. Extract the cell count if it's a laptop battery (e.g., 3-cell, 6-cell).",
        "is_rechargeable": "Boolean. True if the battery is rechargeable."
    }
}